<?xml version="1.0" encoding="UTF-8"?>
<persistence xmlns="http://java.sun.com/xml/ns/persistence" version="2.0">

    <persistence-unit name="NewPersistenceUnit">
        <class>main.models.User</class>
        <class>main.models.UserStatus</class>
        <class>main.models.Country</class>
        <class>main.models.Order</class>
        <class>main.models.OrderLine</class>
        <class>main.models.OrderNote</class>
        <class>main.models.OrderStatus</class>
        <class>main.models.OrderType</class>
        <class>main.models.Product</class>
        <class>main.models.ProductStatus</class>
        <class>main.models.ProductType</class>
        <class>main.models.State</class>
        <class>main.models.UserType</class>
        <properties>
            <property name="hibernate.connection.url" value="jdbc:postgresql://localhost:5432/salesfarce"/>
            <property name="hibernate.connection.driver_class" value="org.postgresql.Driver"/>
        </properties>
    </persistence-unit>
</persistence>
